lsl_xdf_reader/__init__.py
lsl_xdf_reader/data_reader.py
lsl_xdf_reader-0.1.dist-info/LICENSE
lsl_xdf_reader-0.1.dist-info/METADATA
lsl_xdf_reader-0.1.dist-info/WHEEL
lsl_xdf_reader-0.1.dist-info/top_level.txt
lsl_xdf_reader-0.1.dist-info/RECORD
