Metadata-Version: 2.1
Name: lsl_xdf_reader
Version: 0.1
Summary: A package for reading and parsing Lab Streaming Layer (lsl) xdf data
Home-page: https://github.com/metu-humate/lsl-xdf-data-reader
Author: Bartu Atabek
Author-email: batabek@metu.edu.tr
Keywords: xdf data reader,lsl data reader,xdf,lsl,lab streaming layer,xdf reader,lsl reader
Classifier: Development Status :: 5 - Production/Stable
Classifier: Intended Audience :: Science/Research
Classifier: License :: OSI Approved :: MIT License
Classifier: Programming Language :: Python :: 3.12
License-File: LICENSE
